perovscribe/__init__.py
perovscribe/allowed_journals.csv
perovscribe/configuration.py
perovscribe/constants.py
perovscribe/evaluations.py
perovscribe/export.py
perovscribe/llm_call.py
perovscribe/optimizer.py
perovscribe/papersbot.py
perovscribe/pipeline.py
perovscribe/postprocessing.py
perovscribe/pydantic_model_reduced.py
perovscribe/preprocessing/__init__.py
perovscribe/preprocessing/base.py
perovscribe/preprocessing/marker_processor.py
perovscribe/preprocessing/nougat_processor.py
perovscribe/preprocessing/pdf_utils.py
perovscribe/preprocessing/preprocessor.py
perovscribe/preprocessing/pymupdf_processor.py
perovscribe/preprocessing/utils.py
perovscribe-0.0.2.dist-info/licenses/LICENSE
perovscribe-0.0.2.dist-info/METADATA
perovscribe-0.0.2.dist-info/WHEEL
perovscribe-0.0.2.dist-info/entry_points.txt
perovscribe-0.0.2.dist-info/top_level.txt
perovscribe-0.0.2.dist-info/RECORD
