Metadata-Version: 2.4
Name: perovscribe
Version: 0.0.2
Author-email: Sherjeel Shabih <sherjeel.shabih@hu-berlin.de>, Pepe Marquez <jose.marquez@physik.hu-berlin.de>, Kevin Jablonka <mail@kjablonka.com>
License: MIT
Classifier: Programming Language :: Python :: 3.10
Classifier: Programming Language :: Python :: 3.11
Classifier: Programming Language :: Python :: 3.12
Classifier: License :: OSI Approved :: Apache Software License
Classifier: Operating System :: OS Independent
Requires-Python: >=3.10
License-File: LICENSE
Requires-Dist: pydantic
Requires-Dist: litellm
Requires-Dist: diskcache
Requires-Dist: redis
Requires-Dist: pymupdf
Requires-Dist: deepdiff>=8.1.0
Requires-Dist: munkres
Requires-Dist: pint
Requires-Dist: numpy
Requires-Dist: levenshtein
Requires-Dist: instructor
Requires-Dist: fire
Requires-Dist: flatdict
Provides-Extra: dev
Requires-Dist: jupyter; extra == "dev"
Requires-Dist: docformatter; extra == "dev"
Requires-Dist: pytest; extra == "dev"
Requires-Dist: ruff; extra == "dev"
Requires-Dist: bump-my-version; extra == "dev"
Provides-Extra: nougat
Requires-Dist: nougat; extra == "nougat"
Provides-Extra: marker
Requires-Dist: marker-pdf; extra == "marker"
Provides-Extra: pymupdf
Requires-Dist: pymupdf; extra == "pymupdf"
Provides-Extra: docs
Requires-Dist: mkdocs-material>=9.4.0; extra == "docs"
Requires-Dist: mkdocstrings[python]>=0.22.0; extra == "docs"
Requires-Dist: mkdocs-gen-files>=0.5.0; extra == "docs"
Requires-Dist: mkdocs-literate-nav>=0.6.0; extra == "docs"
Requires-Dist: fire; extra == "docs"
Dynamic: license-file
